<annotation>
	<folder>Mohanth</folder>
	<filename>00100sPORTRAIT_00100_BURST20181130210733021_COVER~2.jpg</filename>
	<path>/Users/mohanth/Desktop/Mohanth/00100sPORTRAIT_00100_BURST20181130210733021_COVER~2.jpg</path>
	<source>
		<database>Unknown</database>
	</source>
	<size>
		<width>2448</width>
		<height>3264</height>
		<depth>3</depth>
	</size>
	<segmented>0</segmented>
	<object>
		<name>mohanth</name>
		<pose>Unspecified</pose>
		<truncated>0</truncated>
		<difficult>0</difficult>
		<bndbox>
			<xmin>84</xmin>
			<ymin>816</ymin>
			<xmax>1136</xmax>
			<ymax>1968</ymax>
		</bndbox>
	</object>
</annotation>
