<annotation>
	<folder>Srimanth</folder>
	<filename>DSC01149.jpg</filename>
	<path>/Users/mohanth/Desktop/Srimanth/DSC01149.jpg</path>
	<source>
		<database>Unknown</database>
	</source>
	<size>
		<width>5184</width>
		<height>3888</height>
		<depth>3</depth>
	</size>
	<segmented>0</segmented>
	<object>
		<name>srimanth</name>
		<pose>Unspecified</pose>
		<truncated>0</truncated>
		<difficult>0</difficult>
		<bndbox>
			<xmin>3391</xmin>
			<ymin>1159</ymin>
			<xmax>4223</xmax>
			<ymax>2291</ymax>
		</bndbox>
	</object>
</annotation>
